<?xml version="1.0" encoding="UTF-8"?>
<web-app xmlns="http://java.sun.com/xml/ns/javaee"
         xmlns:xsi="http://www.w3.org/2001/XMLSchema-instance"
         xsi:schemaLocation="http://java.sun.com/xml/ns/javaee http://java.sun.com/xml/ns/javaee/web-app_2_5.xsd"
         version="2.5">

  <display-name>Registry</display-name>

  <filter>
    <filter-name>serviceFilter</filter-name> <!-- do this first- it initializes -->
    <filter-class>edu.stanford.registry.server.service.ServiceFilter</filter-class>
  </filter>
  <filter>
    <filter-name>proxyAuthFilter</filter-name>
    <filter-class>edu.stanford.registry.server.ProxyAuthFilter</filter-class>
  </filter>
  <filter>
    <filter-name>cacheFilter</filter-name>
    <filter-class>edu.stanford.registry.server.CacheFilter</filter-class>
  </filter>
  <filter>
    <filter-name>surveyTokenFilter</filter-name>
    <filter-class>edu.stanford.registry.server.service.SurveyTokenFilter</filter-class>
  </filter>
  <filter>
    <filter-name>serviceAuthFilter</filter-name>
    <filter-class>edu.stanford.registry.server.ServiceProxyAuthFilter</filter-class>
  </filter>

  <filter-mapping>
    <filter-name>proxyAuthFilter</filter-name>
    <url-pattern>/registry/*</url-pattern>
  </filter-mapping>
  <filter-mapping>
    <filter-name>cacheFilter</filter-name>
    <url-pattern>/registry/*</url-pattern>
  </filter-mapping>
  <filter-mapping>
    <filter-name>surveyTokenFilter</filter-name>
    <url-pattern>/patient/*</url-pattern>
  </filter-mapping>
  <filter-mapping>
    <filter-name>serviceAuthFilter</filter-name>
    <url-pattern>/patient/*</url-pattern>
  </filter-mapping>
  <filter-mapping>
    <filter-name>serviceFilter</filter-name>
    <url-pattern>/registry/svc/*</url-pattern>
    <url-pattern>/patient/*</url-pattern>
  </filter-mapping>

  <servlet>
    <servlet-name>ChartServlet</servlet-name>
    <servlet-class>edu.stanford.registry.server.ChartServlet</servlet-class>
    <load-on-startup>3</load-on-startup>
  </servlet>
  <servlet>
    <servlet-name>adapter</servlet-name>
    <servlet-class>org.restlet.ext.servlet.ServerServlet</servlet-class>
    <init-param>
      <param-name>org.restlet.application</param-name>
      <param-value>edu.stanford.registry.server.service.RestletServiceManager</param-value>
    </init-param>
    <init-param>
      <param-name>org.restlet.clients</param-name>
      <param-value>HTTP HTTPS FILE</param-value>
    </init-param>
  </servlet>
  <servlet>
    <servlet-name>clinicService</servlet-name>
    <servlet-class>edu.stanford.registry.server.ClinicServiceImpl</servlet-class>
    <load-on-startup>3</load-on-startup>
  </servlet>
  <servlet>
    <servlet-name>clientService</servlet-name>
    <servlet-class>edu.stanford.registry.server.ClientServiceImpl</servlet-class>
  </servlet>
  <servlet>
    <servlet-name>editorService</servlet-name>
    <servlet-class>edu.stanford.registry.server.EditServiceImpl</servlet-class>
  </servlet>
  <servlet>
    <servlet-name>surveyService</servlet-name>
    <servlet-class>com.seguedevelopment.gwtrpccommlayer.server.GwtRpcCommLayerServlet</servlet-class>
    <init-param>
      <param-name>GwtRpcCommLayerServletImplClass</param-name>
      <param-value>edu.stanford.registry.server.survey.SurveyServiceLocal</param-value>
    </init-param>
    <load-on-startup>3</load-on-startup>
  </servlet>
  <servlet>
    <servlet-name>admin</servlet-name>
    <servlet-class>edu.stanford.registry.server.AdminServiceImpl</servlet-class>
  </servlet>
  <servlet>
    <servlet-name>registrationService</servlet-name>
    <servlet-class>edu.stanford.registry.server.RegistrationServiceImpl</servlet-class>
  </servlet>
  <servlet>
    <servlet-name>securityService</servlet-name>
    <servlet-class>edu.stanford.registry.server.SecurityServiceImpl</servlet-class>
  </servlet>

  <servlet-mapping>
    <servlet-name>ChartServlet</servlet-name>
    <url-pattern>/registry/svc/chart</url-pattern>
  </servlet-mapping>
  <servlet-mapping>
    <servlet-name>adapter</servlet-name>
    <url-pattern>/registry/svc/api/*</url-pattern>
  </servlet-mapping>
  <servlet-mapping>
    <servlet-name>clinicService</servlet-name>
    <url-pattern>/registry/svc/clinicService</url-pattern>
  </servlet-mapping>
  <servlet-mapping>
    <servlet-name>clientService</servlet-name>
    <url-pattern>/registry/svc/clientService</url-pattern>
  </servlet-mapping>
  <servlet-mapping>
    <servlet-name>editorService</servlet-name>
    <url-pattern>/registry/svc/editorService</url-pattern>
  </servlet-mapping>
  <servlet-mapping>
    <servlet-name>surveyService</servlet-name>
    <url-pattern>/patient/survey2</url-pattern>
  </servlet-mapping>
  <servlet-mapping>
    <servlet-name>admin</servlet-name>
    <url-pattern>/registry/svc/admin</url-pattern>
  </servlet-mapping>
  <servlet-mapping>
    <servlet-name>registrationService</servlet-name>
    <url-pattern>/registry/svc/registrationService</url-pattern>
  </servlet-mapping>
  <servlet-mapping>
    <servlet-name>securityService</servlet-name>
    <url-pattern>/registry/svc/securityService</url-pattern>
  </servlet-mapping>
  <servlet>
    <servlet-name>physicianService</servlet-name>
    <servlet-class>edu.stanford.registry.server.PhysicianServiceImpl</servlet-class>
  </servlet>
  <servlet-mapping>
    <servlet-name>physicianService</servlet-name>
    <url-pattern>/registry/svc/physicianService</url-pattern>
  </servlet-mapping>

  <welcome-file-list>
    <welcome-file>Registry.nocache.html</welcome-file>
  </welcome-file-list>

  <mime-mapping>
    <extension>ico</extension>
    <mime-type>image/x-icon</mime-type>
  </mime-mapping>

</web-app>
